games/__init__.py
games/chooser.py
games/controller.py
games/listeners.py
games/manager.py
games/objects.py
games/screen.py
games/scripts.py
games/geo_bash/__init__.py
games/geo_bash/objects.py
games/geo_bash/scenes.py
games/last_survivor/__init__.py
games/last_survivor/objects.py
games/last_survivor/scenes.py
games/number_crush/__init__.py
games/number_crush/objects.py
games/number_crush/scenes.py
games/planet_x/__init__.py
games/planet_x/objects.py
games/planet_x/scenes.py
games/wasp_invasion/__init__.py
games/wasp_invasion/objects.py
games/wasp_invasion/scenes.py
console_games-0.3.5.dist-info/LICENSE
console_games-0.3.5.dist-info/METADATA
console_games-0.3.5.dist-info/WHEEL
console_games-0.3.5.dist-info/entry_points.txt
console_games-0.3.5.dist-info/top_level.txt
console_games-0.3.5.dist-info/RECORD
