Metadata-Version: 2.1
Name: console-games
Version: 0.3.5
Summary: Fun games for macOS/Linux console!
Home-page: https://github.com/maxzheng/console-games
Author: Max Zheng
Author-email: maxzheng.os@gmail.com
License: MIT
Keywords: games terminal console geometry bash number crush math training
Platform: UNKNOWN
Classifier: Development Status :: 5 - Production/Stable
Classifier: Intended Audience :: Developers
Classifier: License :: OSI Approved :: MIT License
Classifier: Programming Language :: Python :: 3
Requires-Python: >=3.5
Requires-Dist: click
